productcategorizationapi/__init__.py
test/__init__.py
websiteclassificationapi/__init__.py
productcategorizationapi-1.3.dist-info/LICENSE
productcategorizationapi-1.3.dist-info/METADATA
productcategorizationapi-1.3.dist-info/WHEEL
productcategorizationapi-1.3.dist-info/top_level.txt
productcategorizationapi-1.3.dist-info/RECORD
