Metadata-Version: 2.1
Name: productcategorizationapi
Version: 1.3
Summary: product categorization API
Home-page: https://www.productcategorization.com
Author-email: info@productcategorizationapi.com
License: UNKNOWN
Keywords: product categorization,classification,categorization
Platform: UNKNOWN
Classifier: License :: OSI Approved :: MIT License
Classifier: Environment :: GPU :: NVIDIA CUDA :: 11.3
Classifier: Environment :: GPU :: NVIDIA CUDA :: 11.0
Classifier: Environment :: GPU :: NVIDIA CUDA
Classifier: Environment :: GPU :: NVIDIA CUDA :: 11.2
Classifier: Environment :: GPU :: NVIDIA CUDA :: 10.1
Classifier: Programming Language :: Python :: 3 :: Only
